Workbook

Sheet Scoring model
A1: Scoring models
A2: Blue cells are weights you can change. Scores on the Prospects tab recalculate. Platform is now a filter column, not a scored criterion, because 31 of 33 prospects scored identically on it and it separated nobody.
A4: PHASE 1 — Speed to first client (current priority)
A5: Optimises for how fast someone will say yes and how quickly you can start testing. Deliberately ignores budget size and client value.
A7: Criterion | B7: Weight | C7: 1 point | D7: 2 points | E7: 3 points
A8: Decision speed | B8: 3 | C8: Enterprise or entrenched agency | D8: Mid-market, some internal process | E8: Owner-managed, one decision maker
A9: Provable problem in hand | B9: 2.5 | C9: Nothing specific, or mature account | D9: Clear gap, needs a call to confirm | E9: Verified finding that costs them money today
A10: Live media to work on | B10: 2 | C10: No paid tags detected | D10: Conversion tag live, ads unconfirmed | E10: Active ads confirmed in the library
A11: Proximity to York | B11: 2 | C11: Over 75 min drive | D11: 45 to 75 min | E11: York or under 45 min
A12: Category fit | B12: 1.5 | C12: Outside the vertical | D12: Other food or drink | E12: Coffee or beer
A13: Maximum possible speed score | B13: =SUM(B8:B12)*3 -> 33
A16: PHASE 2 — Client value (use once you have two case studies)
A17: Ability to pay replaces SKU count as the scale proxy. Fill it from Companies House (employees, net assets, creditors). Until it is filled the value score reads Pending.
A19: Criterion | B19: Weight | C19: 1 point | D19: 2 points | E19: 3 points
A20: Ability to pay | B20: 3 | C20: Under 10 staff or distressed balance sheet | D20: 10 to 49 staff, stable | E20: 50+ staff or known strong trading
A21: Paid media activity | B21: 2 | C21: No tags, no ads | D21: Conversion tag installed, no live ads found | E21: Live ads confirmed on Meta or Google
A22: Commercial scale | B22: 1.5 | C22: Very small catalogue or local only | D22: Regional, moderate range | E22: National distribution or large catalogue
A23: Winnability | B23: 2 | C23: Enterprise with entrenched agency | D23: Mid-market, likely incumbent | E23: Owner-managed, fast decision
A24: Fixable stack gaps | B24: 1.5 | C24: Mature, well run | D24: Some gaps | E24: Obvious fixable problems
A25: Maximum possible value score | B25: =SUM(B20:B24)*3 -> 30
A28: What changed from v1
A29: • Platform fit removed as a criterion. 31 of 33 scored 3, adding a flat 4.5 to everyone and ranking nobody. It is now a filter column.
A30: • Split into two models. Phase 1 ranks speed to a signed client; phase 2 ranks client value. They give very different orders.
A31: • Fixable stack gaps removed from phase 1 scoring as a standalone criterion and replaced by 'provable problem in hand', which requires a specific verified finding rather than a general gap.
A32: • Ability to pay added to phase 2, replacing SKU count as the scale proxy. SKU count was misleading: Theakston has 85 SKUs and GA4 only; Black Sheep has 20 SKUs and national recognition.
A33: • Budget status column added, splitting 'take over an existing budget' from 'create a budget from nothing'. The second group is a much longer sale.
A34: • Commercial model column added (subscription vs transactional). This, not the drink, determines the media playbook.
A35: • Alcohol column added. Alcohol is prohibited on the Shop channel, needs Meta permissions, and Google's alcohol certification regime starts 30 Sep 2026.

Sheet Prospects
A1: Yorkshire prospect list — ranked for speed to first client
A2: Platform, martech and paid activity verified 21 Sep 2026 by fingerprinting each live site, checked against the Meta Ad Library and Google Ads Transparency Center. 'Not detected' means absent from the homepage HTML, which consent gating can cause. Treat it as a question to ask, never a finding to assert in a pitch. Sorted by Speed score, highest first.
A4: Brand | B4: Domain | C4: Town | D4: Drive from York | E4: Category | F4: Alcohol | G4: Commercial model | H4: Budget status | I4: Platform | J4: SKUs | K4: ESP | L4: Reviews | M4: Subscription | N4: Martech detected | O4: Paid media status | P4: Provable problem to lead with | Q4: P1 Decision speed | R4: P1 Provable problem | S4: P1 Live media | T4: P1 Proximity | U4: P1 Category fit | V4: SPEED SCORE | W4: P2 Ability to pay | X4: P2 Paid activity | Y4: P2 Scale | Z4: P2 Winnability | AA4: P2 Stack gaps | AB4: VALUE SCORE | AC4: Status | AD4: Next action
A5: Brew York | B5: brewyork.co.uk | C5: York | D5: York | E5: Craft beer | F5: Yes | G5: Transactional | H5: Tag only | I5: WooCommerce | J5: 261 | K5: Mailchimp | L5: Trustpilot | M5: - | N5: Google Ads AW-10805529416, GA4, Awin, Stripe, Mailchimp, facebook-for-woocommerce AND PixelYourSite | O5: Meta: ads present, mostly inactive. Google: zero ads despite live conversion tag. | P5: Two Meta pixels firing at once (facebook-for-woocommerce and PixelYourSite), double-counting every event and inflating reported conversions. Plus a live Google Ads conversion tag with zero ads running. | Q5: 3 | R5: 3 | S5: 2 | T5: 3 | U5: 3 | V5: =Q5*'Scoring model'!$B$8+R5*'Scoring model'!$B$9+S5*'Scoring model'!$B$10+T5*'Scoring model'!$B$11+U5*'Scoring model'!$B$12 -> 31 | X5: 2 | Y5: 3 | Z5: 3 | AA5: 3 | AB5: =IF(W5="","Pending pay data",W5*'Scoring model'!$B$20+X5*'Scoring model'!$B$21+Y5*'Scoring model'!$B$22+Z5*'Scoring model'!$B$23+AA5*'Scoring model'!$B$24) -> Pending pay data
A6: Northern Monk | B6: northernmonk.com | C6: Leeds | D6: 45-75 min | E6: Craft beer | F6: Yes | G6: Subscription | H6: Live budget | I6: Shopify | J6: - | K6: Klaviyo | L6: Judge.me, Loox, Trustpilot | M6: Recharge | N6: GA4, Klaviyo, Recharge, Judge.me, Loox, Trustpilot | O6: Meta: active ('Fresh From The North'). No Google Ads tag found. | P6: Running Meta with no Google Ads conversion tag detected, so non-brand search is an entirely untested channel on a subscription product. Also paying for three review apps doing one job. | Q6: 2 | R6: 3 | S6: 3 | T6: 2 | U6: 3 | V6: =Q6*'Scoring model'!$B$8+R6*'Scoring model'!$B$9+S6*'Scoring model'!$B$10+T6*'Scoring model'!$B$11+U6*'Scoring model'!$B$12 -> 28 | X6: 3 | Y6: 3 | Z6: 2 | AA6: 3 | AB6: =IF(W6="","Pending pay data",W6*'Scoring model'!$B$20+X6*'Scoring model'!$B$21+Y6*'Scoring model'!$B$22+Z6*'Scoring model'!$B$23+AA6*'Scoring model'!$B$24) -> Pending pay data
A7: Vocation Brewery | B7: vocationbrewery.com | C7: Hebden Bridge | D7: 45-75 min | E7: Craft beer | F7: Yes | G7: Transactional | H7: Live budget | I7: Shopify | J7: 90 | K7: Klaviyo + Attentive | L7: Loox, Trustpilot | M7: - | N7: Google Ads, GA4, Klaviyo, Attentive, Loox, Clarity | O7: Meta: active ('Life & Death', launched w/c 15 Sep 2026). | P7: Running Meta ads with no Meta pixel detected on the homepage. Either consent-gated or a real tracking gap. Verify in a consented session before asserting it. | Q7: 2 | R7: 3 | S7: 3 | T7: 2 | U7: 3 | V7: =Q7*'Scoring model'!$B$8+R7*'Scoring model'!$B$9+S7*'Scoring model'!$B$10+T7*'Scoring model'!$B$11+U7*'Scoring model'!$B$12 -> 28 | X7: 3 | Y7: 2 | Z7: 2 | AA7: 3 | AB7: =IF(W7="","Pending pay data",W7*'Scoring model'!$B$20+X7*'Scoring model'!$B$21+Y7*'Scoring model'!$B$22+Z7*'Scoring model'!$B$23+AA7*'Scoring model'!$B$24) -> Pending pay data
A8: Cosy Cottage Soap | B8: cosycottagesoap.co.uk | C8: York | D8: York | E8: Natural skincare | F8: No | G8: Transactional | H8: Live budget | I8: Shopify | J8: - | K8: Klaviyo | L8: Judge.me, Trustpilot | M8: - | N8: Google Ads, GA4, Klaviyo, Judge.me, Trustpilot, Clarity | O8: Meta: active (seen repeatedly in ad library). | P8: You hold their direct competitor's full paid footprint. Yorkshire Soap went dark on paid in early Sep 2026, which is a concrete share-of-voice opening. | Q8: 3 | R8: 2 | S8: 3 | T8: 3 | U8: 1 | V8: =Q8*'Scoring model'!$B$8+R8*'Scoring model'!$B$9+S8*'Scoring model'!$B$10+T8*'Scoring model'!$B$11+U8*'Scoring model'!$B$12 -> 27.5 | X8: 3 | Y8: 2 | Z8: 3 | AA8: 2 | AB8: =IF(W8="","Pending pay data",W8*'Scoring model'!$B$20+X8*'Scoring model'!$B$21+Y8*'Scoring model'!$B$22+Z8*'Scoring model'!$B$23+AA8*'Scoring model'!$B$24) -> Pending pay data
A9: Yorkshire Handmade Pies | B9: yorkshirehandmadepies.co.uk | C9: Thirsk | D9: Under 45 min | E9: Food | F9: No | G9: Subscription | H9: Tag only | I9: Shopify | J9: 39 | K9: - | L9: Judge.me | M9: Recharge | N9: Google Ads, GA4, Recharge, Judge.me | O9: Google Ads tag live. Meta not confirmed. | P9: Running a Recharge subscription with no ESP detected. A subscription business with no lifecycle email is leaving retention revenue on the table, and retention is what funds acquisition. | Q9: 3 | R9: 2 | S9: 2 | T9: 3 | U9: 2 | V9: =Q9*'Scoring model'!$B$8+R9*'Scoring model'!$B$9+S9*'Scoring model'!$B$10+T9*'Scoring model'!$B$11+U9*'Scoring model'!$B$12 -> 27 | X9: 2 | Y9: 2 | Z9: 3 | AA9: 3 | AB9: =IF(W9="","Pending pay data",W9*'Scoring model'!$B$20+X9*'Scoring model'!$B$21+Y9*'Scoring model'!$B$22+Z9*'Scoring model'!$B$23+AA9*'Scoring model'!$B$24) -> Pending pay data
A10: Sloemotion | B10: sloemotion.com | C10: York | D10: York | E10: Sloe gin and liqueurs | F10: Yes | G10: Transactional | H10: Tag only | I10: Shopify | J10: - | K10: - | L10: Judge.me | M10: - | N10: Meta pixel, Google Ads, GA4, Judge.me, Clarity | O10: Both pixels live, ads not confirmed. | P10: Both acquisition pixels installed and no ESP at all. Paying to acquire traffic with nothing capturing it. York-based so a coffee meeting is trivial. | Q10: 3 | R10: 2 | S10: 2 | T10: 3 | U10: 2 | V10: =Q10*'Scoring model'!$B$8+R10*'Scoring model'!$B$9+S10*'Scoring model'!$B$10+T10*'Scoring model'!$B$11+U10*'Scoring model'!$B$12 -> 27 | X10: 2 | Y10: 1 | Z10: 3 | AA10: 3 | AB10: =IF(W10="","Pending pay data",W10*'Scoring model'!$B$20+X10*'Scoring model'!$B$21+Y10*'Scoring model'!$B$22+Z10*'Scoring model'!$B$23+AA10*'Scoring model'!$B$24) -> Pending pay data
A11: Shepherds Purse | B11: shepherdspurse.co.uk | C11: Thirsk | D11: Under 45 min | E11: Artisan cheese | F11: No | G11: Transactional | H11: Tag only | I11: Shopify | J11: 29 | K11: Klaviyo | L11: Judge.me | M11: - | N11: Google Ads, GA4, Klaviyo, Judge.me | O11: Google Ads tag live. | P11: Google Ads tag live under 45 minutes from York, with Q4 hamper and gifting season about to start. Timing is the hook. | Q11: 3 | R11: 2 | S11: 2 | T11: 3 | U11: 2 | V11: =Q11*'Scoring model'!$B$8+R11*'Scoring model'!$B$9+S11*'Scoring model'!$B$10+T11*'Scoring model'!$B$11+U11*'Scoring model'!$B$12 -> 27 | X11: 2 | Y11: 1 | Z11: 3 | AA11: 2 | AB11: =IF(W11="","Pending pay data",W11*'Scoring model'!$B$20+X11*'Scoring model'!$B$21+Y11*'Scoring model'!$B$22+Z11*'Scoring model'!$B$23+AA11*'Scoring model'!$B$24) -> Pending pay data
A12: Roosters | B12: roosters.co.uk | C12: Harrogate | D12: 45-75 min | E12: Craft beer | F12: Yes | G12: Transactional | H12: Tag only | I12: Shopify | J12: - | K12: - | L12: - | M12: - | N12: Meta pixel, Google Ads, GA4 | O12: Both pixels live, ads not confirmed. | P12: Both acquisition pixels installed, and no ESP and no review app. The entire retention layer is missing behind live acquisition tags. | Q12: 3 | R12: 2 | S12: 2 | T12: 2 | U12: 3 | V12: =Q12*'Scoring model'!$B$8+R12*'Scoring model'!$B$9+S12*'Scoring model'!$B$10+T12*'Scoring model'!$B$11+U12*'Scoring model'!$B$12 -> 26.5 | X12: 2 | Y12: 2 | Z12: 3 | AA12: 3 | AB12: =IF(W12="","Pending pay data",W12*'Scoring model'!$B$20+X12*'Scoring model'!$B$21+Y12*'Scoring model'!$B$22+Z12*'Scoring model'!$B$23+AA12*'Scoring model'!$B$24) -> Pending pay data
A13: Saltaire Brewery | B13: saltairebrewery.com | C13: Shipley | D13: 45-75 min | E13: Craft beer | F13: Yes | G13: Transactional | H13: Tag only | I13: Shopify | J13: - | K13: Klaviyo | L13: Judge.me | M13: - | N13: Google Ads, GA4, Klaviyo, Judge.me | O13: Google Ads tag live. | P13: Canonical Yorkshire brewery stack: Shopify + Klaviyo + Judge.me + Google tag + no Meta pixel + no subscription. One audit template covers this and Ilkley and Black Sheep. | Q13: 3 | R13: 2 | S13: 2 | T13: 2 | U13: 3 | V13: =Q13*'Scoring model'!$B$8+R13*'Scoring model'!$B$9+S13*'Scoring model'!$B$10+T13*'Scoring model'!$B$11+U13*'Scoring model'!$B$12 -> 26.5 | X13: 2 | Y13: 2 | Z13: 3 | AA13: 2 | AB13: =IF(W13="","Pending pay data",W13*'Scoring model'!$B$20+X13*'Scoring model'!$B$21+Y13*'Scoring model'!$B$22+Z13*'Scoring model'!$B$23+AA13*'Scoring model'!$B$24) -> Pending pay data
A14: Ilkley Brewery | B14: ilkleybrewery.co.uk | C14: Ilkley | D14: 45-75 min | E14: Craft beer | F14: Yes | G14: Transactional | H14: Tag only | I14: Shopify | J14: - | K14: Klaviyo | L14: Judge.me | M14: - | N14: Google Ads, GA4, Klaviyo, Judge.me | O14: Google Ads tag live. | P14: Identical stack signature to Saltaire and Black Sheep. The second one you audit costs a fraction of the time of the first. | Q14: 3 | R14: 2 | S14: 2 | T14: 2 | U14: 3 | V14: =Q14*'Scoring model'!$B$8+R14*'Scoring model'!$B$9+S14*'Scoring model'!$B$10+T14*'Scoring model'!$B$11+U14*'Scoring model'!$B$12 -> 26.5 | X14: 2 | Y14: 2 | Z14: 3 | AA14: 2 | AB14: =IF(W14="","Pending pay data",W14*'Scoring model'!$B$20+X14*'Scoring model'!$B$21+Y14*'Scoring model'!$B$22+Z14*'Scoring model'!$B$23+AA14*'Scoring model'!$B$24) -> Pending pay data
A15: Yorkshire Dama Cheese | B15: yorkshiredamacheese.co.uk | C15: Leeds | D15: 45-75 min | E15: Artisan cheese | F15: No | G15: Transactional | H15: No paid detected | I15: Shopify | J15: - | K15: - | L15: - | M15: - | N15: None detected | O15: No tags of any kind detected. | P15: Zero measurement of any kind on a live Shopify store. Nothing to unpick, so the fastest possible technical win. Almost certainly the smallest budget on the list, which makes it a good free pilot. | Q15: 3 | R15: 3 | S15: 1 | T15: 2 | U15: 2 | V15: =Q15*'Scoring model'!$B$8+R15*'Scoring model'!$B$9+S15*'Scoring model'!$B$10+T15*'Scoring model'!$B$11+U15*'Scoring model'!$B$12 -> 25.5 | X15: 1 | Y15: 1 | Z15: 3 | AA15: 3 | AB15: =IF(W15="","Pending pay data",W15*'Scoring model'!$B$20+X15*'Scoring model'!$B$21+Y15*'Scoring model'!$B$22+Z15*'Scoring model'!$B$23+AA15*'Scoring model'!$B$24) -> Pending pay data
A16: Weetons | B16: weetons.com | C16: Harrogate | D16: 45-75 min | E16: Farm shop, hampers | F16: No | G16: Transactional | H16: Tag only | I16: Shopify | J16: 120 | K16: - | L16: - | M16: - | N16: Google Ads, GA4 | O16: Google Ads tag live. | P16: 120 SKUs, hamper-led and therefore heavily Q4, with no ESP and no review app detected. Seasonal concentration is the commercial conversation. | Q16: 3 | R16: 2 | S16: 2 | T16: 2 | U16: 2 | V16: =Q16*'Scoring model'!$B$8+R16*'Scoring model'!$B$9+S16*'Scoring model'!$B$10+T16*'Scoring model'!$B$11+U16*'Scoring model'!$B$12 -> 25 | X16: 2 | Y16: 3 | Z16: 3 | AA16: 3 | AB16: =IF(W16="","Pending pay data",W16*'Scoring model'!$B$20+X16*'Scoring model'!$B$21+Y16*'Scoring model'!$B$22+Z16*'Scoring model'!$B$23+AA16*'Scoring model'!$B$24) -> Pending pay data
... A37: Mamas & Papas | B37: mamasandpapas.com | C37: Huddersfield | D37: 45-75 min | E37: Baby and nursery | F37: No | G37: Transactional | H37: Tag only | I37: Shopify | J37: - | K37: Klaviyo | L37: Trustpilot | M37: - | N37: GA4, Klaviyo, Trustpilot, Clarity | O37: Not confirmed via keyword search; almost certainly advertising. | P37: Large Shopify retailer with no Meta or Google Ads tag detected on the homepage, which is worth a second look given their size. Outside the vertical and a slow buyer. | Q37: 1 | R37: 2 | S37: 2 | T37: 2 | U37: 1 | V37: =Q37*'Scoring model'!$B$8+R37*'Scoring model'!$B$9+S37*'Scoring model'!$B$10+T37*'Scoring model'!$B$11+U37*'Scoring model'!$B$12 -> 17.5 | X37: 3 | Y37: 3 | Z37: 1 | AA37: 2 | AB37: =IF(W37="","Pending pay data",W37*'Scoring model'!$B$20+X37*'Scoring model'!$B$21+Y37*'Scoring model'!$B$22+Z37*'Scoring model'!$B$23+AA37*'Scoring model'!$B$24) -> Pending pay data
A39: Legend
A40: • Yellow cells are scoring inputs (1-3). Edit them and the scores recalculate. Weights live on the 'Scoring model' tab.
A41: • SPEED SCORE ranks how fast you can sign someone and start testing. Use this one now. Max 33.
A42: • VALUE SCORE ranks how much a client is worth. It reads 'Pending pay data' until you fill P2 Ability to pay from Companies House. Max 30.
A43: • Budget status: 'Live budget' means take over existing spend. 'Tag only' means a tag is installed but no ads were found. 'No paid detected' means you would have to sell the concept of paid media first, which is a much longer sale.
A44: • Example row: Status = 'Emailed 22 Sep', Next action = 'Follow up 29 Sep with pixel audit'.

Sheet Phase 1 shortlist
A1: Phase 1 shortlist — get one client, any size
A2: Top 11 by Speed score. Ability to pay is deliberately ignored here. Two or three of these should be run as free or near-free pilots to produce case studies, one in beer and one in coffee, because credibility does not transfer between categories.
A4: Rank | B4: Brand | C4: Speed score | D4: Why this one | E4: Opening line | F4: Known risk
A5: 1 | B5: Brew York | C5: =INDEX(Prospects!$V$5:$V$37,MATCH(B5,Prospects!$A$5:$A$37,0)) -> 31 | D5: York-based, owner-managed, and the single best verified finding on the list. | E5: You have two Meta pixel implementations running at once, facebook-for-woocommerce and PixelYourSite. Every event is being counted twice, so your reported conversions and ROAS are inflated. Separately you have a live Google Ads conversion tag, AW-10805529416, and zero ads running against it. | F5: WooCommerce not Shopify, and net current liabilities of -GBP 83,324 at 31 Mar 2025. They will be price-sensitive. Treat as a paid pilot at a low number.
A6: 2 | B6: Northern Monk | C6: =INDEX(Prospects!$V$5:$V$37,MATCH(B6,Prospects!$A$5:$A$37,0)) -> 28 | D6: Confirmed Meta spend, Recharge subscription, and a whole channel untouched. | E6: You're active on Meta but I can't find a Google Ads conversion tag. On a subscription product, non-brand search is usually the cheapest incremental customer you are not currently buying. | F6: Larger and better resourced than the rest of the list, so more likely to have someone internal already.
A7: 3 | B7: Vocation Brewery | C7: =INDEX(Prospects!$V$5:$V$37,MATCH(B7,Prospects!$A$5:$A$37,0)) -> 28 | D7: Confirmed Meta spend with an apparent tracking gap underneath it. | E7: You launched Life & Death on Meta this month, but I can't detect a Meta pixel on your homepage. If that's consent gating it's a signal-loss question. If it isn't, you're optimising blind. | F7: Verify in a consented browser session before you say this out loud. Cookiebot-style gating produces exactly this false positive.
A8: 4 | B8: Cosy Cottage Soap | C8: =INDEX(Prospects!$V$5:$V$37,MATCH(B8,Prospects!$A$5:$A$37,0)) -> 27.5 | D8: York, active on Meta, and you already hold the competitive picture. | E8: You and Yorkshire Soap are the two York names in this category. They went dark on paid in early September. Here is what they were running and where the gap is now. | F8: Outside the coffee and beer vertical, so it does not build category credibility. Take it for cash flow and process testing, not for the case study.
A9: 5 | B9: Yorkshire Handmade Pies | C9: =INDEX(Prospects!$V$5:$V$37,MATCH(B9,Prospects!$A$5:$A$37,0)) -> 27 | D9: Under 45 minutes, subscription business, obvious missing layer. | E9: You're running a Recharge subscription with no email platform I can detect. Subscription economics live or die on retention, and retention is what lets you outbid everyone on acquisition. | F9: Small catalogue at 39 SKUs. Budget likely modest.
A10: 6 | B10: Sloemotion | C10: =INDEX(Prospects!$V$5:$V$37,MATCH(B10,Prospects!$A$5:$A$37,0)) -> 27 | D10: York, both pixels live, nothing capturing the traffic. | E10: You have both a Meta pixel and a Google Ads tag installed, and no email capture I can see. You're paying to bring people in and letting them leave unrecorded. | F10: Small business, alcohol category, so Shop channel is closed to them and Meta needs permissions.
A11: 7 | B11: Shepherds Purse | C11: =INDEX(Prospects!$V$5:$V$37,MATCH(B11,Prospects!$A$5:$A$37,0)) -> 27 | D11: Under 45 minutes and the seasonal timing is right now. | E11: Your Google Ads tag is live and hamper season starts in about six weeks. Worth knowing whether last Q4's spend actually produced incremental orders before you commit this year's. | F11: 29 SKUs, small budget, and Q4-only relevance.
A12: 8 | B12: Roosters | C12: =INDEX(Prospects!$V$5:$V$37,MATCH(B12,Prospects!$A$5:$A$37,0)) -> 26.5 | D12: Both acquisition pixels live with no retention layer at all. | E12: You've got Meta and Google tags installed and no email platform and no review app. The acquisition is built and nothing is catching what it brings in. | F12: Ads not confirmed in the library, so the spend may be zero. Check before the call.
A13: 9 | B13: Saltaire Brewery | C13: =INDEX(Prospects!$V$5:$V$37,MATCH(B13,Prospects!$A$5:$A$37,0)) -> 26.5 | D13: The canonical Yorkshire brewery stack, so the audit is reusable. | E13: Shopify, Klaviyo, Judge.me, a live Google tag, no Meta pixel and no subscription. That exact combination shows up across most Yorkshire breweries and it has a predictable set of leaks. | F13: Nothing distinctive to lead with. This is a volume play, not a targeted one.
A14: 10 | B14: Ilkley Brewery | C14: =INDEX(Prospects!$V$5:$V$37,MATCH(B14,Prospects!$A$5:$A$37,0)) -> 26.5 | D14: Same stack as Saltaire, so the second audit is near-free to produce. | E14: Same opener as Saltaire. Run them in the same week and reuse the template. | F14: As above.
A15: 11 | B15: Yorkshire Dama Cheese | C15: =INDEX(Prospects!$V$5:$V$37,MATCH(B15,Prospects!$A$5:$A$37,0)) -> 25.5 | D15: Zero tags of any kind. The fastest possible clean win. | E15: You have a live Shopify store with no analytics, no pixel and no tags of any kind. Right now there is no way to know which of your orders came from where. | F15: Almost certainly the smallest budget on the list. Run this one free in exchange for a case study and a reference.
A18: Sequencing note
A19: • Land one beer client and one coffee client before anything else. A coffee roaster will not be persuaded by a brewery case study.
A20: • Yorkshire has roughly 21 breweries and 5 coffee roasters across all three tabs. The beer half is a local play; the coffee half has to run national from the start.
A21: • The three diagnostics that are already proven and repeatable: duplicate pixel firing, conversion tag installed with zero ads running, and Meta ads running with no detectable pixel. All three are verifiable from outside and cost the merchant money today.
A22: • Alcohol clients: Shop channel is closed to them entirely, Meta needs alcohol permissions and age targeting, and Google's alcohol certification regime starts 30 Sep 2026. Generalist agencies avoid this, which is why it is worth learning once.

Sheet Checked not Shopify
A1: Checked and not Shopify
A2: Still viable as agency clients, just not platform fits. Several are migration candidates, which is a second revenue line. Note that two of the five Yorkshire coffee roasters are here.
A4: Brand | B4: Domain | C4: Town | D4: Platform | E4: Note
A5: York Gin | B5: yorkgin.com | C5: York | D5: BigCommerce | E5: Meta pixel and Google Ads both live
A6: Yorkshire Soap Company | B6: yorkshiresoap.co.uk | C6: York | D6: WooCommerce | E6: Paid went dark early Sep 2026
A7: Cooper King Distillery | B7: cooperkingdistillery.co.uk | C7: York | D7: Squarespace | E7: Meta pixel live
A8: Brass Castle Brewery | B8: brasscastle.co.uk | C8: Malton | D8: Squarespace
A9: Wensleydale Creamery | B9: wensleydale.co.uk | C9: Hawes | D9: Visualsoft | E9: Meta, Google Ads and Trustpilot all live
A10: Accent Clothing | B10: accentclothing.com | C10: Leeds | D10: Visualsoft | E10: Meta and Google Ads live
A11: Beer Hawk | B11: beerhawk.co.uk | C11: Knaresborough | D11: Magento | E11: Owned by AB InBev, will have a global agency
A12: Yorkshire Rapeseed Oil | B12: yorkshirerapeseedoil.co.uk | C12: Malton | D12: Magento
A13: Farrah's of Harrogate | B13: farrahs.com | C13: Harrogate | D13: WooCommerce
A14: Fodder | B14: fodder.co.uk | C14: Harrogate | D14: WooCommerce | E14: Meta pixel live
A15: Leeds Brewery | B15: leedsbrewery.co.uk | C15: Leeds | D15: WooCommerce
A16: Turning Point Brew Co | B16: turningpointbrewco.com | C16: Knaresborough | D16: Wix
A17: Abbeydale Brewery | B17: abbeydalebrewery.co.uk | C17: Sheffield | D17: WooCommerce
A18: Roost Coffee | B18: roostcoffee.co.uk | C18: Malton | D18: WooCommerce | E18: COFFEE — one of only five in the region
A19: Yorkshire Pasta Co | B19: yorkshirepasta.co.uk | C19: Malton | D19: WooCommerce | E19: Klaviyo live
A20: Hepworth Brewery | B20: hepworthbrewery.co.uk | C20: Yorkshire | D20: Squarespace
A21: Northern Bloc | B21: northern-bloc.com | C21: Leeds | D21: WordPress
A22: Casa Espresso | B22: casaespresso.co.uk | C22: Bradford | D22: WooCommerce | E22: COFFEE — one of only five in the region
A23: Yorkshire Crisps | B23: yorkshirecrisps.co.uk | C23: Sheffield | D23: WooCommerce

Sheet Blocked by bot protection
A1: Blocked by bot protection — worth a manual look
A3: Brand | B3: Domain | C3: Town | D3: What we saw
A4: Yorkshire Tea / Taylors | B4: yorkshiretea.co.uk | C4: Harrogate | D4: Challenge page, no fingerprints returned
A5: Taylors of Harrogate | B5: taylorsofharrogate.com | C5: Harrogate | D5: Challenge page
A6: Wold Top Brewery | B6: woldtopbrewery.co.uk | C6: Driffield | D6: GA4 and Klaviyo both fired but no platform fingerprint
A7: Pimoroni | B7: pimoroni.com | C7: Sheffield | D7: Challenge page. Large electronics retailer
A8: The Hip Store | B8: thehipstore.co.uk | C8: Bradford | D8: Challenge page
A9: Timothy Taylor | B9: timothytaylor.co.uk | C9: Keighley | D9: GA4 only detected
A10: Henderson's Relish | B10: hendersonsrelish.com | C10: Sheffield | D10: Challenge page
A11: Botham's of Whitby | B11: botham.co.uk | C11: Whitby | D11: GA4 only detected
A12: Lewis & Cooper | B12: lewisandcooper.co.uk | C12: Northallerton | D12: GA4 only detected
A13: Kirkstall Brewery | B13: kirkstallbrewery.com | C13: Leeds | D13: GA4 only detected
A14: Chevin Cycles | B14: chevincycles.com | C14: Otley | D14: Google Ads and GA4 detected, platform unclear
A15: Yorkshire Trading Co | B15: yorkshiretrading.com | C15: Northallerton | D15: GA4 only detected

Sheet Method
A1: Method and sources
B3: Date of research: 21 September 2026. All findings are a point-in-time snapshot.
A5: Platform detection | B5: Each homepage fetched and fingerprinted for platform markers (cdn.shopify.com and /cdn/shop/ for Shopify, Magento_Ui and /static/frontend/ for Magento, wp-content/plugins/woocommerce for WooCommerce). Shopify additionally confirmed where possible via /products.json and /cart.js, which only Shopify serves.
A6: SKU counts | B6: Taken from /products.json (capped at 250 per request) or the product sitemap. A blank means the endpoint was unavailable, not that the catalogue is small.
A7: Martech detection | B7: Regex over rendered homepage HTML for known vendor script hosts and tag ID patterns (GTM-, G-, AW-).
A8: Commercial model | B8: Subscription assigned where a subscription app (Recharge) was detected. Absence of a detected subscription app is recorded as Transactional, which may understate the count: some subscription implementations are native or custom and leave no homepage fingerprint.
A9: IMPORTANT CAVEAT | B9: Consent management platforms block tags until a visitor accepts cookies. A tag recorded as 'not detected' may simply be gated. Bettys is a confirmed example, its Meta pixel does not fire before Cookiebot consent. Treat 'not detected' as a question to ask, not a finding to assert in a pitch.
A10: Deep dives | B10: Bettys and Brew York were behind bot protection (Imperva/Incapsula and an anti-bot challenge) and were inspected in a real browser session instead.
A12: Paid media verification | B12: Meta Ad Library — https://www.facebook.com/ads/library/ | Google Ads Transparency Center — https://adstransparency.google.com/
A13: Company data | B13: Companies House. Brew York Limited 09607690, accounts to 31 March 2025 filed 24 December 2025: 98 employees (prior year 78), net assets GBP 579,591, cash GBP 238,666, net current liabilities NEGATIVE GBP 83,324 versus positive GBP 241,438 the year before, short-term creditors GBP 1,226,201 up 52%. Bettys & Taylors Group Ltd 00500829. Brew York figures are from filleted small-company accounts, which omit the profit and loss statement, so turnover is not disclosed and is not estimated here.
A15: OUTSTANDING WORK | B15: P2 Ability to pay is unfilled for all 33 prospects. Scripted pass against the Companies House API for employee count, net assets and creditors. This is the only variable not yet measured and it determines which prospects can actually pay a retainer.
B16: Estimated monthly spend not captured. Ad Library active-ad volume and creative refresh rate give a usable band. TOG24 at ~100 active ads is a different proposition from Vocation at one campaign.
B17: Incumbent agency not captured. Creative quality and production patterns in the Ad Library indicate whether someone competent is already on the account.
A19: Alcohol compliance | B19: Alcohol is prohibited on the Shopify Shop channel (help.shopify.com, prohibited products on Shop). Meta requires alcohol advertising permissions and age targeting. Google's revised alcohol advertising policy takes effect 30 September 2026 and introduces certification requirements. 17 of the 33 prospects are alcohol brands.
